utilsrama/_common.py
utilsrama/_psutil_linux.cpython-35m-i386-linux-gnu.so
utilsrama/_pssunos.py
utilsrama/_pslinux.py
utilsrama/_psbsd.py
utilsrama/_psosx.py
utilsrama/_psaix.py
utilsrama/_compat.py
utilsrama/_psutil_posix.cpython-35m-i386-linux-gnu.so
utilsrama/_psposix.py
utilsrama/_pswindows.py
utilsrama/__init__.py
utilsrama/tests/test_connections.py
utilsrama/tests/__main__.py
utilsrama/tests/runner.py
utilsrama/tests/test_unicode.py
utilsrama/tests/test_osx.py
utilsrama/tests/test_misc.py
utilsrama/tests/test_contracts.py
utilsrama/tests/test_bsd.py
utilsrama/tests/test_linux.py
utilsrama/tests/test_system.py
utilsrama/tests/test_process.py
utilsrama/tests/test_sunos.py
utilsrama/tests/test_aix.py
utilsrama/tests/test_memleaks.py
utilsrama/tests/__init__.py
utilsrama/tests/test_testutils.py
utilsrama/tests/test_windows.py
utilsrama/tests/test_posix.py
utilsrama-0.0.4.dist-info/WHEEL
utilsrama-0.0.4.dist-info/METADATA
utilsrama-0.0.4.dist-info/top_level.txt
utilsrama-0.0.4.dist-info/RECORD
