Metadata-Version: 2.1
Name: utilsrama
Version: 0.0.4
Summary: UNKNOWN
Home-page: UNKNOWN
License: UNKNOWN
Platform: Platform Independent
Classifier: Programming Language :: Python :: 3.5
Classifier: Programming Language :: Python :: 3.6
Classifier: Programming Language :: Python :: 3.7
Classifier: Programming Language :: Python :: 3.8
Requires-Python: >=2.6, !=3.0.*, !=3.1.*, !=3.2.*, !=3.3.*
Provides-Extra: test
Requires-Dist: ipaddress ; (python_version < "3.0") and extra == 'test'
Requires-Dist: mock ; (python_version < "3.0") and extra == 'test'
Requires-Dist: unittest2 ; (python_version < "3.0") and extra == 'test'
Requires-Dist: enum34 ; (python_version <= "3.4") and extra == 'test'
Requires-Dist: pywin32 ; (sys_platform == "win32") and extra == 'test'
Requires-Dist: wmi ; (sys_platform == "win32") and extra == 'test'
